setup.cfg
setup.py
robin_pl/__init__.py
robin_pl.egg-info/PKG-INFO
robin_pl.egg-info/SOURCES.txt
robin_pl.egg-info/dependency_links.txt
robin_pl.egg-info/not-zip-safe
robin_pl.egg-info/top_level.txt