Metadata-Version: 1.0
Name: robin-pl
Version: 0.5.30
Summary: It is programming language in russian!
Home-page: UNKNOWN
Author: FotonPC
Author-email: foton-pc@inbox.ru
License: UNKNOWN
Platform: UNKNOWN
